{"S\u00c4UGETIERE":{"0":"Primaten","1":"Microcebus murinus","2":"Nycticebus bengalensis","3":"Nycticebus coucang","4":"Galago senegalensis","5":"Callimico goeldii","6":"Callithrix geo  royi","7":"Saguinus imperator\rsubgrisecens","8":"Saguinus nigricollis","9":"Saguinus oedipus","10":"Cebus olivaceus","11":"Saimiri sciureus","12":"Aotus azarae","13":"Callicebus cupreus","14":"Alouatta caraya","15":"Ateles fusciceps ru  ventris","16":"Cercopithecus hamlyni","17":"Macaca fuscata","18":"Macaca silenus","19":"Macaca sinica","20":"Mandrillus sphinx","21":"Papio hamadryas","22":"Semnopithecus entellus","23":"Trachypithecus auratus","24":"Hylobates pileatus","25":"Symphalangus syndactylus","26":"Gorilla gorilla gorilla","27":"Pan paniscus","28":"Pan troglodytes","29":"Pan troglodytes schweinfurthii","30":"Pan troglodytes verus","31":"Pongo pygmaeus"},"MAMMALIA":{"0":"Primates","1":"1","2":"0","3":"1","4":"1","5":"1","6":"1","7":"1","8":"1","9":"1","10":"5","11":"1","12":"3","13":"3","14":"0","15":"1","16":"1","17":"8","18":"2","19":"8","20":"2","21":"17","22":"1","23":"0","24":"1","25":"3","26":"1","27":"3","28":"1","29":"1","30":"0","31":"2"},"2019":{"0":"m","1":"2","2":"1","3":"1","4":"5","5":"1","6":"1","7":"1","8":"0","9":"1","10":"3","11":"5","12":"4","13":"1","14":"1","15":"1","16":"2","17":"8","18":"7","19":"5","20":"2","21":"24","22":"3","23":"2","24":"0","25":"1","26":"4","27":"3","28":"2","29":"0","30":"1","31":"3"},"geboren":{"0":"w","1":"0","2":"0","3":"0","4":"0","5":"0","6":"0","7":"0","8":"0","9":"0","10":"0","11":"3","12":"0","13":"0","14":"0","15":"0","16":"0","17":"0","18":"0","19":"0","20":"0","21":"0","22":"0","23":"0","24":"0","25":"0","26":"0","27":"0","28":"0","29":"0","30":"0","31":"0"},"Zug\u00e4nge":{"0":"u","1":"0","2":"0","3":"0","4":"0","5":"0","6":"0","7":"0","8":"0","9":"0","10":"0","11":"0","12":"0","13":"0","14":"0","15":"0","16":"0","17":"0","18":"0","19":"0","20":"0","21":"1","22":"0","23":"0","24":"0","25":"0","26":"0","27":"0","28":"0","29":"0","30":"0","31":"0"},"gestorben":{"0":"m","1":"0","2":"0","3":"0","4":"0","5":"0","6":"0","7":"0","8":"0","9":"1","10":"0","11":"0","12":"0","13":"0","14":"0","15":"0","16":"1","17":"0","18":"0","19":"0","20":"0","21":"0","22":"0","23":"0","24":"0","25":"0","26":"0","27":"1","28":"0","29":"0","30":"0","31":"0"},"Abgabe":{"0":"w","1":"0","2":"0","3":"0","4":"0","5":"0","6":"0","7":"0","8":"0","9":"1","10":"0","11":"5","12":"0","13":"0","14":"0","15":"0","16":"0","17":"0","18":"0","19":"0","20":"0","21":"8","22":"0","23":"0","24":"0","25":"0","26":"0","27":"0","28":"0","29":"0","30":"0","31":"0"},"2020":{"0":"u","1":"0","2":"0","3":"0","4":"0","5":"0","6":"0","7":"0","8":"0","9":"0","10":"0","11":"0","12":"0","13":"0","14":"0","15":"0","16":"0","17":"0","18":"0","19":"0","20":"0","21":"0","22":"0","23":"0","24":"0","25":"0","26":"0","27":"0","28":"0","29":"0","30":"0","31":"0"},"Unnamed: 0":{"0":"m","1":"0","2":"0","3":"0","4":"0","5":"0","6":"0","7":"0","8":"0","9":"0","10":"0","11":"0","12":"0","13":"0","14":"0","15":"0","16":"0","17":"0","18":"0","19":"0","20":"0","21":"0","22":"0","23":"0","24":"0","25":"0","26":"0","27":"0","28":"0","29":"0","30":"0","31":"0"},"Unnamed: 1":{"0":"w","1":"0","2":"0","3":"0","4":"0","5":"0","6":"0","7":"0","8":"0","9":"0","10":"0","11":"0","12":"0","13":"0","14":"0","15":"0","16":"0","17":"0","18":"0","19":"0","20":"0","21":"0","22":"0","23":"0","24":"0","25":"0","26":"0","27":"0","28":"0","29":"0","30":"0","31":"0"},"Unnamed: 2":{"0":"u","1":"1","2":"0","3":"0","4":"0","5":"0","6":"0","7":"1","8":"0","9":"0","10":"2","11":"0","12":"0","13":"0","14":"0","15":"0","16":"0","17":"0","18":"0","19":"0","20":"0","21":"0","22":"0","23":"0","24":"0","25":"1","26":"0","27":"0","28":"0","29":"0","30":"0","31":"0"},"Unnamed: 3":{"0":"m","1":"1","2":"0","3":"1","4":"1","5":"1","6":"1","7":"0","8":"0","9":"1","10":"0","11":"0","12":"0","13":"0","14":"0","15":"0","16":"0","17":"0","18":"0","19":"0","20":"0","21":"3","22":"1","23":"0","24":"0","25":"0","26":"0","27":"0","28":"0","29":"0","30":"0","31":"0"},"Unnamed: 4":{"0":"w","1":"0","2":"0","3":"0","4":"0","5":"0","6":"0","7":"0","8":"0","9":"1","10":"0","11":"2","12":"0","13":"0","14":"0","15":"0","16":"0","17":"0","18":"0","19":"0","20":"0","21":"7","22":"0","23":"0","24":"0","25":"0","26":"0","27":"0","28":"0","29":"0","30":"0","31":"0"},"Unnamed: 5":{"0":"u","1":"0","2":"0","3":"0","4":"0","5":"0","6":"0","7":"0","8":"0","9":"0","10":"0","11":"2","12":"0","13":"0","14":"0","15":"0","16":"0","17":"0","18":"0","19":"0","20":"0","21":"0","22":"0","23":"0","24":"0","25":"0","26":"0","27":"0","28":"0","29":"0","30":"0","31":"0"},"Unnamed: 6":{"0":"m","1":"0","2":"0","3":"0","4":"0","5":"0","6":"0","7":"0","8":"0","9":"0","10":"0","11":"0","12":"0","13":"0","14":"1","15":"0","16":"0","17":"0","18":"0","19":"0","20":"0","21":"0","22":"0","23":"2","24":"0","25":"0","26":"0","27":"0","28":"0","29":"0","30":"0","31":"1"},"Unnamed: 7":{"0":"w","1":"0","2":"0","3":"0","4":"0","5":"0","6":"0","7":"0","8":"0","9":"0","10":"0","11":"0","12":"0","13":"0","14":"0","15":"0","16":"0","17":"0","18":"0","19":"0","20":"0","21":"0","22":"0","23":"0","24":"0","25":"0","26":"0","27":"0","28":"0","29":"0","30":"0","31":"0"},"Unnamed: 8":{"0":"u","1":"0","2":"0","3":"1","4":"1","5":"1","6":"1","7":"0","8":"1","9":"1","10":"3","11":"1","12":"3","13":"3","14":"0","15":"1","16":"1","17":"8","18":"2","19":"8","20":"2","21":"18","22":"1","23":"0","24":"1","25":"2","26":"1","27":"3","28":"1","29":"1","30":"0","31":"2"},"Unnamed: 9":{"0":"m","1":"1","2":"1","3":"0","4":"4","5":"0","6":"0","7":"1","8":"0","9":"1","10":"3","11":"6","12":"4","13":"1","14":"0","15":"1","16":"3","17":"8","18":"7","19":"5","20":"2","21":"21","22":"2","23":"0","24":"0","25":"1","26":"4","27":"4","28":"2","29":"0","30":"1","31":"2"},"Unnamed: 10":{"0":"w","1":null,"2":null,"3":null,"4":null,"5":null,"6":null,"7":null,"8":null,"9":null,"10":null,"11":null,"12":null,"13":null,"14":null,"15":null,"16":null,"17":null,"18":null,"19":null,"20":null,"21":null,"22":null,"23":null,"24":null,"25":null,"26":null,"27":null,"28":null,"29":null,"30":null,"31":null},"Unnamed: 11":{"0":"u","1":null,"2":null,"3":null,"4":null,"5":null,"6":null,"7":null,"8":null,"9":null,"10":null,"11":null,"12":null,"13":null,"14":null,"15":null,"16":null,"17":null,"18":null,"19":null,"20":null,"21":null,"22":null,"23":null,"24":null,"25":null,"26":null,"27":null,"28":null,"29":null,"30":null,"31":null}}